{"title":"Chapter 5 — Organising and tidying data","markdown":{"yaml":{"title":"Chapter 5 — Organising and tidying data"},"headingText":"Chapter 5","containsRefs":false,"markdown":"\n\n::: {.chapter-hero}\n\n## Organising and tidying data\n\nThis chapter moves from the project folder to the data file itself. The aim is to make datasets easier to check, analyse, document and reuse, without pretending that all real-world data arrive clean or simple.\n:::\n\n::: {.chapter-overview}\n### What this chapter does\n\nChapter 3 focused on where project materials live: folders, filenames, raw and derived files, and lightweight versioning. Chapter 4 focused on the Data Management Plan as the record of decisions, responsibilities and constraints.\n\nThis chapter focuses on the **structure and quality of the data files themselves**. It covers common spreadsheet risks, tidy data principles, missing data, exclusions, data dictionaries and simple checks that make data easier to analyse and defend.\n:::\n\n## Learning objectives\n\nBy the end of this chapter, you should be able to:\n\n- explain why messy data make analysis fragile;\n- recognise common spreadsheet and data-entry risks;\n- describe the core principles of tidy data;\n- distinguish raw, cleaned and analysis-ready data without repeating the full project-organisation chapter;\n- document missingness, exclusions and filtering decisions;\n- identify minimum checks that should be carried out before analysis;\n- create or improve a simple data dictionary/codebook.\n\n::: {.callout-note}\n### Boundary with other chapters\n\nThis chapter is **not** mainly about folder structures or file naming. Those are covered in Chapter 3. It is also not mainly about governance, storage or access. Those are covered in Chapter 4.\n\nHere, the question is simpler: **is the dataset itself structured so that it can be understood, checked and analysed safely?**\n:::\n\n## If the data are messy, everything is fragile\n\nMessy data make research harder to check, rerun, defend and reuse. Problems that look small during data entry can become substantial later, especially when data are linked, cleaned, merged or analysed by someone else.\n\nCommon consequences include:\n\n- analysing the wrong version of a dataset;\n- treating missing values as real values;\n- mixing text and numeric values in the same column;\n- losing information that was stored only in formatting or comments;\n- introducing manual corrections that cannot be reproduced;\n- making code more complicated than it needs to be.\n\nData Carpentry emphasises that small changes in spreadsheet formatting can improve efficiency and reliability when data are later cleaned and analysed [@datacarpentry_spreadsheet_errors].\n\n::: {.activity-box}\n### Quick reflection\n\nHave you ever analysed, cleaned or shared the wrong version of a dataset?\n\nIf so, what made the error possible?\n\n- unclear filename;\n- mixed raw and cleaned data;\n- missing documentation;\n- manual edits;\n- several versions stored in different places;\n- no clear owner or approval point.\n:::\n\n## What makes a dataset usable?\n\nA usable dataset is not necessarily perfect. It is one that is sufficiently clear, consistent and documented for its intended purpose.\n\nA usable dataset should make the following visible:\n\n::: {.practice-grid}\n\n::: {.practice-card}\n### Structure\n\nRows, columns and tables have clear meanings.\n:::\n\n::: {.practice-card}\n### Meaning\n\nVariables, units, categories and codes are documented.\n:::\n\n::: {.practice-card}\n### Provenance\n\nIt is clear where the data came from and how they changed.\n:::\n\n::: {.practice-card}\n### Quality\n\nMissing values, exclusions and known limitations are recorded.\n:::\n\n:::\n\nWhite and colleagues describe practical data-reuse principles that are also useful for the original research team: provide metadata, preserve an unprocessed form of the data, use standard formats, use good null values, and make the data easy to import and understand [@white2013reuse].\n\n## Spreadsheet risks\n\nSpreadsheets are useful for viewing, checking and small-scale data entry. They are also risky when they become the main place where cleaning, coding, analysis and documentation happen invisibly.\n\nCommon risks include:\n\n- **mixed data types**: numbers, dates and text in the same column;\n- **hidden formatting**: colours, font styles or cell comments used to convey meaning;\n- **manual edits**: changes made by hand without a script or log;\n- **implicit missing values**: blanks, `NA`, `N/A`, `0`, `-999` or text used inconsistently;\n- **merged cells**: useful for visual display but difficult for analysis software;\n- **multiple tables in one sheet**: visually convenient but machine-unfriendly;\n- **multiple tabs with inconsistent structures**: hard to combine and check later;\n- **dates automatically changed by software**.\n\n::: {.callout-warning}\n### Spreadsheet rule of thumb\n\nUse spreadsheets for inspection and controlled data entry where appropriate. Avoid using formatting, colours, comments or manual edits as the only record of information that matters for analysis.\n:::\n\n## A minimum spreadsheet standard\n\nWhere spreadsheets are used, keep them boring and machine-readable.\n\nA minimum standard is:\n\n- one table per sheet;\n- one header row;\n- one variable per column;\n- one observation per row;\n- no merged cells;\n- no blank rows or columns inside the data table;\n- no totals, graphs or notes embedded in the data table;\n- explicit and documented missing-value codes;\n- dates entered consistently, preferably using ISO format `YYYY-MM-DD`;\n- export or archive an analysis version as `.csv` where appropriate.\n\n::: {.figure-box}\n### From human-readable to analysis-ready\n\nA human-readable spreadsheet might combine address information in one cell:\n\n| address |\n|---|\n| 170 Kessels Road Nathan Qld 4111 Australia |\n| 1 Parklands Dr, Southport QLD 4215 |\n\nAn analysis-ready table separates the components that may need to be checked, cleaned or linked:\n\n| street_number | street_name | street_type | suburb | state | postcode | country |\n|---:|---|---|---|---|---:|---|\n| 170 | Kessels | Road | Nathan | Qld | 4111 | Australia |\n| 1 | Parklands | Drive | Southport | Qld | 4215 | Australia |\n\nThis does not mean every dataset must be split into the smallest possible units. It means the structure should reflect how the data will be checked, analysed and reused.\n:::\n\n## Tidy data: the core idea\n\nTidy data is a simple but powerful way to structure rectangular datasets. Wickham summarises tidy data as a structure where each variable is a column, each observation is a row, and each type of observational unit forms a table [@wickham2014tidy].\n\nFor practical purposes, start with these three rules:\n\n::: {.definition-grid}\n\n::: {.definition-card}\n### One variable per column\n\nEach column should contain one kind of information, such as date of birth, postcode, exposure value, or outcome status.\n:::\n\n::: {.definition-card}\n### One observation per row\n\nEach row should represent one unit of analysis: for example, one participant, one school, one measurement, one visit, or one time period.\n:::\n\n::: {.definition-card}\n### One value per cell\n\nAvoid storing multiple pieces of information in one cell when they may need to be analysed separately.\n:::\n\n:::\n\nTidy data are easier to search, filter, join, visualise and analyse. They also reduce the amount of special-purpose code needed to interpret the file.\n\n::: {.callout-note}\n### Tidy does not mean final\n\nA tidy dataset is not automatically correct, complete or analysis-ready. It still needs provenance, definitions, quality checks and documentation.\n:::\n\n## Raw, cleaned and analysis-ready data\n\nChapter 3 introduced the principle of separating raw, derived and output files. In this chapter, the same principle matters because a dataset can change through several states.\n\n::: {.practice-grid}\n\n::: {.practice-card}\n### Raw data\n\nThe data as received, collected or extracted. These should be protected from overwrite.\n:::\n\n::: {.practice-card}\n### Cleaned data\n\nData where formats, labels and obvious inconsistencies have been standardised. Cleaning steps should be scripted or documented.\n:::\n\n::: {.practice-card}\n### Analysis-ready data\n\nData prepared for a specific analysis, with exclusions, derived variables and linkage decisions applied.\n:::\n\n:::\n\nThe important point is not the exact folder name. The important point is that someone can tell **which version is closest to the original source**, **which version has been cleaned**, and **which version was used for a specific result**.\n\n## Data provenance and lineage\n\nData provenance describes where data came from, what happened to them, and how outputs were produced. CESSDA frames data-file structure as part of organising and documenting research data so that files remain understandable over time [@cessda_data_file_structure].\n\nFor each important dataset, you should be able to answer:\n\n- What is the original source?\n- Who provided or created it?\n- When was it received, extracted or generated?\n- What cleaning steps were applied?\n- What variables were derived?\n- What records were excluded?\n- Which script or workflow created the analysis-ready version?\n- Which outputs or publications used this version?\n\n::: {.figure-box}\n### A simple data lineage record\n\n```{mermaid}\nflowchart LR\n    A[Raw data received] --> B[Cleaning script]\n    B --> C[Cleaned dataset]\n    C --> D[Derivation / linkage]\n    D --> E[Analysis-ready dataset]\n    E --> F[Tables, figures, model outputs]\n\n    B -. record decisions .-> G[Decision log]\n    D -. record exclusions .-> G\n    E -. describe variables .-> H[Data dictionary]\n```\n\nThis is the minimum story someone needs in order to understand how the analysis dataset was produced.\n:::\n\n## Missing data and exclusions\n\nMissing data are not just a technical nuisance. They can change the interpretation of results, the analytic sample and the conclusions.\n\nGood practice includes:\n\n- using explicit and consistent missing-value codes;\n- distinguishing true zero from missing or not applicable;\n- documenting why data are missing when known;\n- recording exclusions and filtering decisions;\n- reporting how missingness was handled in analysis.\n\nKang describes missing data as a problem that requires attention to the pattern and mechanism of missingness, as well as the method used to handle it [@kang2013missing]. For this workshop, the main message is practical: **do not let missingness become invisible**.\n\n::: {.callout-important}\n### Missing values need definitions\n\nA blank cell, `0`, `NA`, `N/A`, `-999`, `unknown` and `not applicable` do not mean the same thing unless you define them.\n\nIn R, `NA` is often appropriate for missing values. In a shared dataset or spreadsheet, the meaning of any missing-value code should be stated in the data dictionary.\n:::\n\n## Exclusions and filtering decisions\n\nExclusions should be visible and justifiable. This is particularly important when exclusions affect sample size, bias, precision or the interpretation of inequalities.\n\nA minimum record should include:\n\n| Item | Example |\n|---|---|\n| Exclusion rule | Exclude records with missing postcode |\n| Rationale | Exposure assignment requires geocoding |\n| Number excluded | 184 records, 3.2% of sample |\n| Timing | Applied before exposure linkage |\n| Script or decision record | `02_clean_addresses.R`, decision log entry 2025-02-12 |\n| Sensitivity check | Results compared with missing-postcode group described separately |\n\n::: {.callout-warning}\n### Avoid hidden exclusions\n\nDo not delete rows manually and leave no trace. Use a scripted filter where possible, and record the rule and rationale in a decision log, README or analysis note.\n:::\n\n## Data dictionaries and codebooks\n\nA data dictionary or codebook explains what each variable means. It is one of the most useful low-burden reproducibility tools.\n\nA simple data dictionary should include:\n\n- variable name;\n- short description;\n- source dataset;\n- data type;\n- units, if relevant;\n- allowed values or categories;\n- missing-value codes;\n- derivation rule, if the variable was created;\n- notes or known limitations.\n\n::: {.figure-box}\n### Minimal data dictionary example\n\n| variable | description | source | type | allowed values / units | missing code | notes |\n|---|---|---|---|---|---|---|\n| `response_id` | Unique survey response identifier | Census 2021 | character | 17-character string | blank | Not personally identifying |\n| `postcode` | Residential postcode at survey date | Survey | character | Valid UK postcode | `NA` | Standardised before linkage |\n| `pm25_annual` | Annual mean PM2.5 exposure | Modelled exposure | numeric | µg/m³ | `NA` | Linked by postcode centroid |\n| `excluded` | Record excluded from main analysis | Derived | logical | `TRUE` / `FALSE` | none | Rationale in `exclusion_reason` |\n:::\n\n## Basic checks before analysis\n\nSome checks are simple but high-value. They do not require a formal testing framework.\n\nBefore analysis, ask:\n\n- Does the dataset have the expected number of rows and columns?\n- Are required variables present?\n- Are key variables the expected type?\n- Are dates in one format?\n- Are numeric variables within plausible ranges?\n- Are categorical variables using expected labels?\n- Are missing values coded consistently?\n- Are duplicate records expected or accidental?\n- Has the analytic sample size changed since the previous version?\n\nThese checks belong naturally in the code-quality chapter as well. Here, the focus is on **what to check in the data**. Chapter 7 will cover **how to implement these checks in R code**.\n\n## Messy data activity\n\n::: {.activity-box}\n### Activity: identify the risks\n\nLook at the example below and identify what would make it difficult to analyse safely.\n\n| Date | Age | Where was the article | Blood type | Preferred Gender |\n|---|---:|---|---|---|\n| 23/1/2023 | 32 | United States | AB | Female |\n| Feb-17 | 54 |  | A | N/A |\n| 2/2/2000 | 12 | USA | 0 | Male |\n| 23-Mar-93 | 53 | Brisbane, Australia | #NAME? | Mail |\n\nQuestions:\n\n- Are dates recorded consistently?\n- Is `Age` the right variable, or would date of birth plus date of measurement be more stable?\n- Are locations recorded consistently?\n- Is `0` a valid blood type, a missing code, or an error?\n- What does `N/A` mean here?\n- Is `Mail` a spelling mistake or a valid category?\n- What has Excel or spreadsheet software changed automatically?\n:::\n\n::: {.callout-tip}\n### Possible fixes\n\n- Use a consistent date format, preferably `YYYY-MM-DD`.\n- Consider recording date of birth rather than age if age depends on timing.\n- Split location into structured fields where useful, such as country, region and city.\n- Define missing-value codes explicitly.\n- Use controlled categories for gender and blood type where appropriate.\n- Keep a data dictionary so future users understand all valid codes.\n:::\n\n## Minimum viable practice\n\nFor most projects, a realistic minimum is:\n\n::: {.practice-grid}\n\n::: {.practice-card}\n### Protect the raw data\n\nKeep a copy of the data as received. Do not overwrite it.\n:::\n\n::: {.practice-card}\n### Use one analysis dataset\n\nMake clear which cleaned or analysis-ready file was used for each analysis.\n:::\n\n::: {.practice-card}\n### Create a data dictionary\n\nDocument variables, units, categories and missing codes.\n:::\n\n::: {.practice-card}\n### Record exclusions\n\nState what was removed, why, when and by whom.\n:::\n\n:::\n\n## Beginner and advanced next steps\n\n::: {.activity-box}\n### Choose one action\n\n**Beginner**\n\n- Decide how missing values will be represented.\n- Use `YYYY-MM-DD` for dates.\n- Create a short data dictionary for one dataset.\n- Save an analysis-ready copy separately from the raw data.\n\n**Advanced**\n\n- Add automated checks for row counts, variable names and plausible ranges.\n- Create a scripted cleaning pipeline from raw to analysis-ready data.\n- Add exclusion counts to the analysis report.\n- Use controlled vocabularies or metadata standards where appropriate.\n:::\n\n## Recommended resources for this chapter\n\n- Data Carpentry: common spreadsheet formatting problems [@datacarpentry_spreadsheet_errors]\n- Wickham: tidy data principles [@wickham2014tidy]\n- White et al.: practical data reuse recommendations [@white2013reuse]\n- Kang: prevention and handling of missing data [@kang2013missing]\n- CESSDA: designing a data file structure [@cessda_data_file_structure]\n\n## What comes next?\n\nThe next chapter moves from data-file structure to documentation. We will look at README files, data dictionaries, metadata, decision logs, changelogs, environment notes and protocols.\n\n::: {.chapter-summary}\n## Key takeaways\n\n- Messy data make analysis fragile, even when the project folder is well organised.\n- Spreadsheets are useful but risky when formatting, comments or manual edits carry analytical meaning.\n- Tidy data principles make datasets easier to check, analyse and reuse.\n- Missing values and exclusions need explicit definitions and records.\n- A data dictionary is one of the simplest and most valuable reproducibility tools.\n- Chapter 7 will show how to implement some of these checks in R code.\n:::\n","srcMarkdownNoYaml":"\n\n::: {.chapter-hero}\n# Chapter 5\n\n## Organising and tidying data\n\nThis chapter moves from the project folder to the data file itself. The aim is to make datasets easier to check, analyse, document and reuse, without pretending that all real-world data arrive clean or simple.\n:::\n\n::: {.chapter-overview}\n### What this chapter does\n\nChapter 3 focused on where project materials live: folders, filenames, raw and derived files, and lightweight versioning. Chapter 4 focused on the Data Management Plan as the record of decisions, responsibilities and constraints.\n\nThis chapter focuses on the **structure and quality of the data files themselves**. It covers common spreadsheet risks, tidy data principles, missing data, exclusions, data dictionaries and simple checks that make data easier to analyse and defend.\n:::\n\n## Learning objectives\n\nBy the end of this chapter, you should be able to:\n\n- explain why messy data make analysis fragile;\n- recognise common spreadsheet and data-entry risks;\n- describe the core principles of tidy data;\n- distinguish raw, cleaned and analysis-ready data without repeating the full project-organisation chapter;\n- document missingness, exclusions and filtering decisions;\n- identify minimum checks that should be carried out before analysis;\n- create or improve a simple data dictionary/codebook.\n\n::: {.callout-note}\n### Boundary with other chapters\n\nThis chapter is **not** mainly about folder structures or file naming. Those are covered in Chapter 3. It is also not mainly about governance, storage or access. Those are covered in Chapter 4.\n\nHere, the question is simpler: **is the dataset itself structured so that it can be understood, checked and analysed safely?**\n:::\n\n## If the data are messy, everything is fragile\n\nMessy data make research harder to check, rerun, defend and reuse. Problems that look small during data entry can become substantial later, especially when data are linked, cleaned, merged or analysed by someone else.\n\nCommon consequences include:\n\n- analysing the wrong version of a dataset;\n- treating missing values as real values;\n- mixing text and numeric values in the same column;\n- losing information that was stored only in formatting or comments;\n- introducing manual corrections that cannot be reproduced;\n- making code more complicated than it needs to be.\n\nData Carpentry emphasises that small changes in spreadsheet formatting can improve efficiency and reliability when data are later cleaned and analysed [@datacarpentry_spreadsheet_errors].\n\n::: {.activity-box}\n### Quick reflection\n\nHave you ever analysed, cleaned or shared the wrong version of a dataset?\n\nIf so, what made the error possible?\n\n- unclear filename;\n- mixed raw and cleaned data;\n- missing documentation;\n- manual edits;\n- several versions stored in different places;\n- no clear owner or approval point.\n:::\n\n## What makes a dataset usable?\n\nA usable dataset is not necessarily perfect. It is one that is sufficiently clear, consistent and documented for its intended purpose.\n\nA usable dataset should make the following visible:\n\n::: {.practice-grid}\n\n::: {.practice-card}\n### Structure\n\nRows, columns and tables have clear meanings.\n:::\n\n::: {.practice-card}\n### Meaning\n\nVariables, units, categories and codes are documented.\n:::\n\n::: {.practice-card}\n### Provenance\n\nIt is clear where the data came from and how they changed.\n:::\n\n::: {.practice-card}\n### Quality\n\nMissing values, exclusions and known limitations are recorded.\n:::\n\n:::\n\nWhite and colleagues describe practical data-reuse principles that are also useful for the original research team: provide metadata, preserve an unprocessed form of the data, use standard formats, use good null values, and make the data easy to import and understand [@white2013reuse].\n\n## Spreadsheet risks\n\nSpreadsheets are useful for viewing, checking and small-scale data entry. They are also risky when they become the main place where cleaning, coding, analysis and documentation happen invisibly.\n\nCommon risks include:\n\n- **mixed data types**: numbers, dates and text in the same column;\n- **hidden formatting**: colours, font styles or cell comments used to convey meaning;\n- **manual edits**: changes made by hand without a script or log;\n- **implicit missing values**: blanks, `NA`, `N/A`, `0`, `-999` or text used inconsistently;\n- **merged cells**: useful for visual display but difficult for analysis software;\n- **multiple tables in one sheet**: visually convenient but machine-unfriendly;\n- **multiple tabs with inconsistent structures**: hard to combine and check later;\n- **dates automatically changed by software**.\n\n::: {.callout-warning}\n### Spreadsheet rule of thumb\n\nUse spreadsheets for inspection and controlled data entry where appropriate. Avoid using formatting, colours, comments or manual edits as the only record of information that matters for analysis.\n:::\n\n## A minimum spreadsheet standard\n\nWhere spreadsheets are used, keep them boring and machine-readable.\n\nA minimum standard is:\n\n- one table per sheet;\n- one header row;\n- one variable per column;\n- one observation per row;\n- no merged cells;\n- no blank rows or columns inside the data table;\n- no totals, graphs or notes embedded in the data table;\n- explicit and documented missing-value codes;\n- dates entered consistently, preferably using ISO format `YYYY-MM-DD`;\n- export or archive an analysis version as `.csv` where appropriate.\n\n::: {.figure-box}\n### From human-readable to analysis-ready\n\nA human-readable spreadsheet might combine address information in one cell:\n\n| address |\n|---|\n| 170 Kessels Road Nathan Qld 4111 Australia |\n| 1 Parklands Dr, Southport QLD 4215 |\n\nAn analysis-ready table separates the components that may need to be checked, cleaned or linked:\n\n| street_number | street_name | street_type | suburb | state | postcode | country |\n|---:|---|---|---|---|---:|---|\n| 170 | Kessels | Road | Nathan | Qld | 4111 | Australia |\n| 1 | Parklands | Drive | Southport | Qld | 4215 | Australia |\n\nThis does not mean every dataset must be split into the smallest possible units. It means the structure should reflect how the data will be checked, analysed and reused.\n:::\n\n## Tidy data: the core idea\n\nTidy data is a simple but powerful way to structure rectangular datasets. Wickham summarises tidy data as a structure where each variable is a column, each observation is a row, and each type of observational unit forms a table [@wickham2014tidy].\n\nFor practical purposes, start with these three rules:\n\n::: {.definition-grid}\n\n::: {.definition-card}\n### One variable per column\n\nEach column should contain one kind of information, such as date of birth, postcode, exposure value, or outcome status.\n:::\n\n::: {.definition-card}\n### One observation per row\n\nEach row should represent one unit of analysis: for example, one participant, one school, one measurement, one visit, or one time period.\n:::\n\n::: {.definition-card}\n### One value per cell\n\nAvoid storing multiple pieces of information in one cell when they may need to be analysed separately.\n:::\n\n:::\n\nTidy data are easier to search, filter, join, visualise and analyse. They also reduce the amount of special-purpose code needed to interpret the file.\n\n::: {.callout-note}\n### Tidy does not mean final\n\nA tidy dataset is not automatically correct, complete or analysis-ready. It still needs provenance, definitions, quality checks and documentation.\n:::\n\n## Raw, cleaned and analysis-ready data\n\nChapter 3 introduced the principle of separating raw, derived and output files. In this chapter, the same principle matters because a dataset can change through several states.\n\n::: {.practice-grid}\n\n::: {.practice-card}\n### Raw data\n\nThe data as received, collected or extracted. These should be protected from overwrite.\n:::\n\n::: {.practice-card}\n### Cleaned data\n\nData where formats, labels and obvious inconsistencies have been standardised. Cleaning steps should be scripted or documented.\n:::\n\n::: {.practice-card}\n### Analysis-ready data\n\nData prepared for a specific analysis, with exclusions, derived variables and linkage decisions applied.\n:::\n\n:::\n\nThe important point is not the exact folder name. The important point is that someone can tell **which version is closest to the original source**, **which version has been cleaned**, and **which version was used for a specific result**.\n\n## Data provenance and lineage\n\nData provenance describes where data came from, what happened to them, and how outputs were produced. CESSDA frames data-file structure as part of organising and documenting research data so that files remain understandable over time [@cessda_data_file_structure].\n\nFor each important dataset, you should be able to answer:\n\n- What is the original source?\n- Who provided or created it?\n- When was it received, extracted or generated?\n- What cleaning steps were applied?\n- What variables were derived?\n- What records were excluded?\n- Which script or workflow created the analysis-ready version?\n- Which outputs or publications used this version?\n\n::: {.figure-box}\n### A simple data lineage record\n\n```{mermaid}\nflowchart LR\n    A[Raw data received] --> B[Cleaning script]\n    B --> C[Cleaned dataset]\n    C --> D[Derivation / linkage]\n    D --> E[Analysis-ready dataset]\n    E --> F[Tables, figures, model outputs]\n\n    B -. record decisions .-> G[Decision log]\n    D -. record exclusions .-> G\n    E -. describe variables .-> H[Data dictionary]\n```\n\nThis is the minimum story someone needs in order to understand how the analysis dataset was produced.\n:::\n\n## Missing data and exclusions\n\nMissing data are not just a technical nuisance. They can change the interpretation of results, the analytic sample and the conclusions.\n\nGood practice includes:\n\n- using explicit and consistent missing-value codes;\n- distinguishing true zero from missing or not applicable;\n- documenting why data are missing when known;\n- recording exclusions and filtering decisions;\n- reporting how missingness was handled in analysis.\n\nKang describes missing data as a problem that requires attention to the pattern and mechanism of missingness, as well as the method used to handle it [@kang2013missing]. For this workshop, the main message is practical: **do not let missingness become invisible**.\n\n::: {.callout-important}\n### Missing values need definitions\n\nA blank cell, `0`, `NA`, `N/A`, `-999`, `unknown` and `not applicable` do not mean the same thing unless you define them.\n\nIn R, `NA` is often appropriate for missing values. In a shared dataset or spreadsheet, the meaning of any missing-value code should be stated in the data dictionary.\n:::\n\n## Exclusions and filtering decisions\n\nExclusions should be visible and justifiable. This is particularly important when exclusions affect sample size, bias, precision or the interpretation of inequalities.\n\nA minimum record should include:\n\n| Item | Example |\n|---|---|\n| Exclusion rule | Exclude records with missing postcode |\n| Rationale | Exposure assignment requires geocoding |\n| Number excluded | 184 records, 3.2% of sample |\n| Timing | Applied before exposure linkage |\n| Script or decision record | `02_clean_addresses.R`, decision log entry 2025-02-12 |\n| Sensitivity check | Results compared with missing-postcode group described separately |\n\n::: {.callout-warning}\n### Avoid hidden exclusions\n\nDo not delete rows manually and leave no trace. Use a scripted filter where possible, and record the rule and rationale in a decision log, README or analysis note.\n:::\n\n## Data dictionaries and codebooks\n\nA data dictionary or codebook explains what each variable means. It is one of the most useful low-burden reproducibility tools.\n\nA simple data dictionary should include:\n\n- variable name;\n- short description;\n- source dataset;\n- data type;\n- units, if relevant;\n- allowed values or categories;\n- missing-value codes;\n- derivation rule, if the variable was created;\n- notes or known limitations.\n\n::: {.figure-box}\n### Minimal data dictionary example\n\n| variable | description | source | type | allowed values / units | missing code | notes |\n|---|---|---|---|---|---|---|\n| `response_id` | Unique survey response identifier | Census 2021 | character | 17-character string | blank | Not personally identifying |\n| `postcode` | Residential postcode at survey date | Survey | character | Valid UK postcode | `NA` | Standardised before linkage |\n| `pm25_annual` | Annual mean PM2.5 exposure | Modelled exposure | numeric | µg/m³ | `NA` | Linked by postcode centroid |\n| `excluded` | Record excluded from main analysis | Derived | logical | `TRUE` / `FALSE` | none | Rationale in `exclusion_reason` |\n:::\n\n## Basic checks before analysis\n\nSome checks are simple but high-value. They do not require a formal testing framework.\n\nBefore analysis, ask:\n\n- Does the dataset have the expected number of rows and columns?\n- Are required variables present?\n- Are key variables the expected type?\n- Are dates in one format?\n- Are numeric variables within plausible ranges?\n- Are categorical variables using expected labels?\n- Are missing values coded consistently?\n- Are duplicate records expected or accidental?\n- Has the analytic sample size changed since the previous version?\n\nThese checks belong naturally in the code-quality chapter as well. Here, the focus is on **what to check in the data**. Chapter 7 will cover **how to implement these checks in R code**.\n\n## Messy data activity\n\n::: {.activity-box}\n### Activity: identify the risks\n\nLook at the example below and identify what would make it difficult to analyse safely.\n\n| Date | Age | Where was the article | Blood type | Preferred Gender |\n|---|---:|---|---|---|\n| 23/1/2023 | 32 | United States | AB | Female |\n| Feb-17 | 54 |  | A | N/A |\n| 2/2/2000 | 12 | USA | 0 | Male |\n| 23-Mar-93 | 53 | Brisbane, Australia | #NAME? | Mail |\n\nQuestions:\n\n- Are dates recorded consistently?\n- Is `Age` the right variable, or would date of birth plus date of measurement be more stable?\n- Are locations recorded consistently?\n- Is `0` a valid blood type, a missing code, or an error?\n- What does `N/A` mean here?\n- Is `Mail` a spelling mistake or a valid category?\n- What has Excel or spreadsheet software changed automatically?\n:::\n\n::: {.callout-tip}\n### Possible fixes\n\n- Use a consistent date format, preferably `YYYY-MM-DD`.\n- Consider recording date of birth rather than age if age depends on timing.\n- Split location into structured fields where useful, such as country, region and city.\n- Define missing-value codes explicitly.\n- Use controlled categories for gender and blood type where appropriate.\n- Keep a data dictionary so future users understand all valid codes.\n:::\n\n## Minimum viable practice\n\nFor most projects, a realistic minimum is:\n\n::: {.practice-grid}\n\n::: {.practice-card}\n### Protect the raw data\n\nKeep a copy of the data as received. Do not overwrite it.\n:::\n\n::: {.practice-card}\n### Use one analysis dataset\n\nMake clear which cleaned or analysis-ready file was used for each analysis.\n:::\n\n::: {.practice-card}\n### Create a data dictionary\n\nDocument variables, units, categories and missing codes.\n:::\n\n::: {.practice-card}\n### Record exclusions\n\nState what was removed, why, when and by whom.\n:::\n\n:::\n\n## Beginner and advanced next steps\n\n::: {.activity-box}\n### Choose one action\n\n**Beginner**\n\n- Decide how missing values will be represented.\n- Use `YYYY-MM-DD` for dates.\n- Create a short data dictionary for one dataset.\n- Save an analysis-ready copy separately from the raw data.\n\n**Advanced**\n\n- Add automated checks for row counts, variable names and plausible ranges.\n- Create a scripted cleaning pipeline from raw to analysis-ready data.\n- Add exclusion counts to the analysis report.\n- Use controlled vocabularies or metadata standards where appropriate.\n:::\n\n## Recommended resources for this chapter\n\n- Data Carpentry: common spreadsheet formatting problems [@datacarpentry_spreadsheet_errors]\n- Wickham: tidy data principles [@wickham2014tidy]\n- White et al.: practical data reuse recommendations [@white2013reuse]\n- Kang: prevention and handling of missing data [@kang2013missing]\n- CESSDA: designing a data file structure [@cessda_data_file_structure]\n\n## What comes next?\n\nThe next chapter moves from data-file structure to documentation. We will look at README files, data dictionaries, metadata, decision logs, changelogs, environment notes and protocols.\n\n::: {.chapter-summary}\n## Key takeaways\n\n- Messy data make analysis fragile, even when the project folder is well organised.\n- Spreadsheets are useful but risky when formatting, comments or manual edits carry analytical meaning.\n- Tidy data principles make datasets easier to check, analyse and reuse.\n- Missing values and exclusions need explicit definitions and records.\n- A data dictionary is one of the simplest and most valuable reproducibility tools.\n- Chapter 7 will show how to implement some of these checks in R code.\n:::\n"},"formats":{"html":{"identifier":{"display-name":"HTML","target-format":"html","base-format":"html"},"execute":{"fig-width":7,"fig-height":5,"fig-format":"retina","fig-dpi":96,"df-print":"default","error":false,"eval":true,"cache":null,"freeze":"auto","echo":true,"output":true,"warning":true,"include":true,"keep-md":false,"keep-ipynb":false,"ipynb":null,"enabled":null,"daemon":null,"daemon-restart":false,"debug":false,"ipynb-filters":[],"engine":"markdown"},"render":{"keep-tex":false,"keep-source":false,"keep-hidden":false,"prefer-html":false,"output-divs":true,"output-ext":"html","fig-align":"default","fig-pos":null,"fig-env":null,"code-fold":"none","code-overflow":"wrap","code-link":false,"code-line-numbers":false,"code-tools":false,"tbl-colwidths":"auto","merge-includes":true,"inline-includes":false,"preserve-yaml":false,"latex-auto-mk":true,"latex-auto-install":true,"latex-clean":true,"latex-max-runs":10,"latex-makeindex":"makeindex","latex-makeindex-opts":[],"latex-tlmgr-opts":[],"latex-input-paths":[],"latex-output-dir":null,"link-external-icon":false,"link-external-newwindow":true,"self-contained-math":false,"format-resources":[],"notebook-links":true,"format-links":true},"pandoc":{"standalone":true,"wrap":"none","default-image-extension":"png","to":"html","css":["style.css"],"number-sections":false,"toc":true,"toc-depth":3,"output-file":"05-organise-tidy.html"},"language":{"toc-title-document":"Table of contents","toc-title-website":"On this page","related-formats-title":"Other Formats","related-notebooks-title":"Notebooks","source-notebooks-prefix":"Source","section-title-abstract":"Abstract","section-title-appendices":"Appendices","section-title-footnotes":"Footnotes","section-title-references":"References","section-title-reuse":"Reuse","section-title-copyright":"Copyright","section-title-citation":"Citation","appendix-attribution-cite-as":"For attribution, please cite this work as:","appendix-attribution-bibtex":"BibTeX citation:","title-block-author-single":"Author","title-block-author-plural":"Authors","title-block-affiliation-single":"Affiliation","title-block-affiliation-plural":"Affiliations","title-block-published":"Published","title-block-modified":"Modified","callout-tip-title":"Tip","callout-note-title":"Note","callout-warning-title":"Warning","callout-important-title":"Important","callout-caution-title":"Caution","code-summary":"Code","code-tools-menu-caption":"Code","code-tools-show-all-code":"Show All Code","code-tools-hide-all-code":"Hide All Code","code-tools-view-source":"View Source","code-tools-source-code":"Source Code","code-line":"Line","code-lines":"Lines","copy-button-tooltip":"Copy to Clipboard","copy-button-tooltip-success":"Copied!","repo-action-links-edit":"Edit this page","repo-action-links-source":"View source","repo-action-links-issue":"Report an issue","back-to-top":"Back to top","search-no-results-text":"No results","search-matching-documents-text":"matching documents","search-copy-link-title":"Copy link to search","search-hide-matches-text":"Hide additional matches","search-more-match-text":"more match in this document","search-more-matches-text":"more matches in this document","search-clear-button-title":"Clear","search-detached-cancel-button-title":"Cancel","search-submit-button-title":"Submit","search-label":"Search","toggle-section":"Toggle section","toggle-sidebar":"Toggle sidebar navigation","toggle-dark-mode":"Toggle dark mode","toggle-reader-mode":"Toggle reader mode","toggle-navigation":"Toggle navigation","crossref-fig-title":"Figure","crossref-tbl-title":"Table","crossref-lst-title":"Listing","crossref-thm-title":"Theorem","crossref-lem-title":"Lemma","crossref-cor-title":"Corollary","crossref-prp-title":"Proposition","crossref-cnj-title":"Conjecture","crossref-def-title":"Definition","crossref-exm-title":"Example","crossref-exr-title":"Exercise","crossref-ch-prefix":"Chapter","crossref-apx-prefix":"Appendix","crossref-sec-prefix":"Section","crossref-eq-prefix":"Equation","crossref-lof-title":"List of Figures","crossref-lot-title":"List of Tables","crossref-lol-title":"List of Listings","environment-proof-title":"Proof","environment-remark-title":"Remark","environment-solution-title":"Solution","listing-page-order-by":"Order By","listing-page-order-by-default":"Default","listing-page-order-by-date-asc":"Oldest","listing-page-order-by-date-desc":"Newest","listing-page-order-by-number-desc":"High to Low","listing-page-order-by-number-asc":"Low to High","listing-page-field-date":"Date","listing-page-field-title":"Title","listing-page-field-description":"Description","listing-page-field-author":"Author","listing-page-field-filename":"File Name","listing-page-field-filemodified":"Modified","listing-page-field-subtitle":"Subtitle","listing-page-field-readingtime":"Reading Time","listing-page-field-categories":"Categories","listing-page-minutes-compact":"{0} min","listing-page-category-all":"All","listing-page-no-matches":"No matching items"},"metadata":{"lang":"en","fig-responsive":true,"quarto-version":"1.3.433","bibliography":["references.bib"],"csl":"nature.csl","theme":"cosmo","code-copy":true,"smooth-scroll":true,"link-citations":true,"title":"Chapter 5 — Organising and tidying data"},"extensions":{"book":{"multiFile":true}}}},"projectFormats":["html"]}